python_avro_generator/__init__.py
python_avro_generator/codegen.py
python_avro_generator-1.1.3.dist-info/METADATA
python_avro_generator-1.1.3.dist-info/WHEEL
python_avro_generator-1.1.3.dist-info/top_level.txt
python_avro_generator-1.1.3.dist-info/RECORD
