Metadata-Version: 2.1
Name: python-avro-generator
Version: 1.1.3
Summary: Python Avro codegen for Le Comptoir Des Pharmacies
Home-page: https://bitbucket.org/lecomptoirdespharmacies/lcdp-openapi-codegen
Author: Le Comptoir Des Pharmacies
Author-email: g.thrasibule@lecomptoirdespharmacies.fr
License: Apache-2.0
Keywords: openapi,python-avro-generator,openapi3
Platform: UNKNOWN
Requires-Dist: lcdp-api
Requires-Dist: lcdp-avro-to-python (==0.3.3.post8)
